perlcompat/__init__.py
perlcompat-1.1.dist-info/LICENSE
perlcompat-1.1.dist-info/METADATA
perlcompat-1.1.dist-info/WHEEL
perlcompat-1.1.dist-info/top_level.txt
perlcompat-1.1.dist-info/RECORD
