Metadata-Version: 2.1
Name: perlcompat
Version: 1.1
Summary: Perl-like utility functions such as warn, die, getopt, and require
Home-page: https://github.com/h-ohsaki/perlcompat
Author: Hiroyuki Ohsaki
Author-email: h-ohsaki@lsnl.jp
License: UNKNOWN
Platform: UNKNOWN
Classifier: Programming Language :: Python :: 3
Classifier: License :: OSI Approved :: GNU General Public License v3 (GPLv3)
Classifier: Operating System :: OS Independent
